htmlclasses/__init__.py
htmlclasses/htmlclasses.py
htmlclasses/lib/__init__.py
htmlclasses/lib/drawing/__init__.py
htmlclasses/lib/drawing/core.py
htmlclasses/lib/drawing/plot2d.py
htmlclasses/lib/svg.py
htmlclasses/serialize.py
htmlclasses-0.3.2.dist-info/LICENSE
htmlclasses-0.3.2.dist-info/WHEEL
htmlclasses-0.3.2.dist-info/METADATA
htmlclasses-0.3.2.dist-info/RECORD
