Metadata-Version: 2.1
Name: htmlclasses
Version: 0.3.2
Summary: Python in, HTML out.
Home-page: https://github.com/uigctaw/htmlclasses
Author: uigctaw
Author-email: uigctaw@protonmail.com
Requires-Python: >=3.9,<4.0
Classifier: Programming Language :: Python :: 3
Classifier: Programming Language :: Python :: 3.9
